{"cameraMode":{"drawMode":0,"name":"Shaded","section":"Shading Mode"},"sceneLighting":false,"audioPlay":false,"sceneViewState":{"m_AlwaysRefresh":false,"showFog":true,"showSkybox":false,"showFlares":true,"showImageEffects":true,"showParticleSystems":true,"showVisualEffectGraphs":true,"m_FxEnabled":true},"in2DMode":false,"pivot":{"x":3.1731607913970949,"y":1.3975074291229249,"z":2.6385929584503176},"rotation":{"x":0.5421198606491089,"y":0.026461457833647729,"z":-0.017069628462195398,"w":0.839652955532074},"size":7.794228553771973,"orthographic":false}